Metadata-Version: 2.1
Name: odoo13-addon-procurement-purchase-sale-no-grouping
Version: 13.0.1.0.1.dev2
Summary: Procurement Purchase Service No Grouping
Home-page: https://github.com/OCA/purchase-workflow
Author: Tecnativa,Odoo Community Association (OCA)
Author-email: support@odoo-community.org
License: AGPL-3
Platform: UNKNOWN
Classifier: Programming Language :: Python
Classifier: Framework :: Odoo
Classifier: Framework :: Odoo :: 13.0
Classifier: License :: OSI Approved :: GNU Affero General Public License v3
Requires-Python: >=3.5
Requires-Dist: odoo13-addon-procurement-purchase-no-grouping
Requires-Dist: odoo <13.1dev,>=13.0a
